jsonpycraft/__init__.py
jsonpycraft/core/__init__.py
jsonpycraft/core/errors.py
jsonpycraft/core/singleton.py
jsonpycraft/core/types.py
jsonpycraft/json/__init__.py
jsonpycraft/json/base.py
jsonpycraft/json/io.py
jsonpycraft/json/list.py
jsonpycraft/json/map.py
jsonpycraft/manager/__init__.py
jsonpycraft/manager/configuration.py
jsonpycraft-0.1.8.dist-info/LICENSE
jsonpycraft-0.1.8.dist-info/METADATA
jsonpycraft-0.1.8.dist-info/WHEEL
jsonpycraft-0.1.8.dist-info/RECORD
