Metadata-Version: 2.3
Name: jsonpycraft
Version: 0.1.8
Summary: JsonPyCraft is a specialized Python toolkit designed for efficient and structured JSON management.
License: AGPL-3.0-or-later
Author: Austin Berrio
Author-email: aberrio@teleprint.me
Requires-Python: >=3.12
Classifier: License :: OSI Approved :: GNU Affero General Public License v3 or later (AGPLv3+)
Classifier: Programming Language :: Python :: 3
Classifier: Programming Language :: Python :: 3.12
Classifier: Programming Language :: Python :: 3.13
Requires-Dist: python-dotenv (>=1.1.0,<2.0.0)
Project-URL: Documentation, https://github.com/teleprint-me/json-py-craft/tree/main/docs
Project-URL: Source, https://github.com/teleprint-me/json-py-craft
